depth.py
tree.py
triegig-0.0.1.dist-info/LICENSE.txt
triegig-0.0.1.dist-info/METADATA
triegig-0.0.1.dist-info/WHEEL
triegig-0.0.1.dist-info/top_level.txt
triegig-0.0.1.dist-info/RECORD
