Metadata-Version: 2.1
Name: triegig
Version: 0.0.1
Summary: User-Interactive Trie that allows users to add, remove, search, and emulate search prefix guess.
Home-page: UNKNOWN
License: UNKNOWN
Platform: UNKNOWN
